{
	"features":[
		{
			"geometry":{
				"coordinates":[
					[
						[
							[
								86.42396819,
								46.33695300
							],
							[
								86.40501421,
								46.34381475
							],
							[
								86.39934640,
								46.34587109
							],
							[
								86.37893501,
								46.34576361
							],
							[
								86.29967347,
								46.35054281
							],
							[
								86.29908375,
								46.35057877
							],
							[
								86.28923329,
								46.35213361
							],
							[
								86.27492059,
								46.35339430
							],
							[
								86.26709585,
								46.35808099
							],
							[
								86.26216285,
								46.35950594
							],
							[
								86.25641384,
								46.35784897
							],
							[
								86.24619837,
								46.36401028
							],
							[
								86.24291381,
								46.36276559
							],
							[
								86.22740932,
								46.36115334
							],
							[
								86.22525425,
								46.35922738
							],
							[
								86.22478856,
								46.35881193
							],
							[
								86.22818665,
								46.35614551
							],
							[
								86.22921810,
								46.35502019
							],
							[
								86.23071615,
								46.35227200
							],
							[
								86.23750456,
								46.34854346
							],
							[
								86.24635140,
								46.34439848
							],
							[
								86.25553584,
								46.34024945
							],
							[
								86.26823313,
								46.33455381
							],
							[
								86.27483567,
								46.33360130
							],
							[
								86.28443572,
								46.32736713
							],
							[
								86.29188977,
								46.32397873
							],
							[
								86.30105493,
								46.32094117
							],
							[
								86.31800806,
								46.31349997
							],
							[
								86.33102084,
								46.30926448
							],
							[
								86.32759611,
								46.30683971
							],
							[
								86.32057697,
								46.30157636
							],
							[
								86.31385665,
								46.29500493
							],
							[
								86.32139103,
								46.27849998
							],
							[
								86.33286314,
								46.26708487
							],
							[
								86.33585931,
								46.26470470
							],
							[
								86.33674685,
								46.24778960
							],
							[
								86.33723006,
								46.23858272
							],
							[
								86.30778198,
								46.21012954
							],
							[
								86.30435963,
								46.15925591
							],
							[
								86.31323954,
								46.13182799
							],
							[
								86.33672573,
								46.05919660
							],
							[
								86.46548148,
								46.04895627
							],
							[
								86.46823495,
								46.09185084
							],
							[
								86.46630655,
								46.10317461
							],
							[
								86.46409924,
								46.11612823
							],
							[
								86.45893146,
								46.14753146
							],
							[
								86.44287657,
								46.17372311
							],
							[
								86.43843174,
								46.18501878
							],
							[
								86.43834353,
								46.18524170
							],
							[
								86.43826535,
								46.18537962
							],
							[
								86.43817214,
								46.18554452
							],
							[
								86.43702660,
								46.18756429
							],
							[
								86.43651550,
								46.18819669
							],
							[
								86.43069407,
								46.19541159
							],
							[
								86.42988865,
								46.19640986
							],
							[
								86.43556406,
								46.19754572
							],
							[
								86.43646681,
								46.19921148
							],
							[
								86.44059526,
								46.20967560
							],
							[
								86.44472510,
								46.21205838
							],
							[
								86.44795979,
								46.22633986
							],
							[
								86.45264087,
								46.24699391
							],
							[
								86.44076486,
								46.26169240
							],
							[
								86.43852686,
								46.27972814
							],
							[
								86.44265503,
								46.30464806
							],
							[
								86.44311693,
								46.32739999
							],
							[
								86.44315292,
								46.32917627
							],
							[
								86.44316992,
								46.33002441
							],
							[
								86.42396819,
								46.33695300
							]
						]
					]
				],
				"type":"MultiPolygon"
			},
			"properties":{
				"center":[
					86.34651175,
					46.20648328
				],
				"centroid":[
					86.34651175,
					46.20648328
				],
				"childrenNum":0,
				"id":661004,
				"level":"district",
				"name":"一八四团",
				"parent":{
					"adcode":660000
				}
			},
			"type":"Feature"
		}
	],
	"type":"FeatureCollection"
}